google_calendar_to_sqlite/__init__.py
google_calendar_to_sqlite/cli.py
google_calendar_to_sqlite/utils.py
google_calendar_to_sqlite-0.1a0.dist-info/LICENSE
google_calendar_to_sqlite-0.1a0.dist-info/METADATA
google_calendar_to_sqlite-0.1a0.dist-info/WHEEL
google_calendar_to_sqlite-0.1a0.dist-info/entry_points.txt
google_calendar_to_sqlite-0.1a0.dist-info/top_level.txt
google_calendar_to_sqlite-0.1a0.dist-info/RECORD
